escodegen/__init__.py
escodegen/escodegen.py
escodegen-1.0.10.dist-info/METADATA
escodegen-1.0.10.dist-info/WHEEL
escodegen-1.0.10.dist-info/licenses/LICENSE
escodegen-1.0.10.dist-info/RECORD
