Metadata-Version: 2.1
Name: escodegen
Version: 1.0.10
Summary: ECMAScript code generator
Project-URL: Homepage, https://github.com/0o120/escodegen-python
Author-email: 0x78 <contact@0x78.com>
License-File: LICENSE
Keywords: ast,ecmascript,escodegen,generate,generator,javascript
Classifier: Development Status :: 5 - Production/Stable
Classifier: Intended Audience :: Developers
Classifier: License :: OSI Approved :: BSD License
Classifier: Programming Language :: Python :: 3.6
Classifier: Topic :: Software Development :: Code Generators
Classifier: Topic :: Software Development :: Compilers
Classifier: Topic :: Software Development :: Libraries :: Python Modules
Classifier: Topic :: Text Processing :: General
Requires-Python: >=3.6
Requires-Dist: esutils
